MANIFEST.in
README.txt
collective.cutandpaste-configure.zcml
setup.py
collective/__init__.py
collective.cutandpaste.egg-info/PKG-INFO
collective.cutandpaste.egg-info/SOURCES.txt
collective.cutandpaste.egg-info/dependency_links.txt
collective.cutandpaste.egg-info/entry_points.txt
collective.cutandpaste.egg-info/namespace_packages.txt
collective.cutandpaste.egg-info/not-zip-safe
collective.cutandpaste.egg-info/requires.txt
collective.cutandpaste.egg-info/top_level.txt
collective/cutandpaste/README.txt
collective/cutandpaste/__init__.py
collective/cutandpaste/blueprint.py
collective/cutandpaste/configure.zcml
collective/cutandpaste/cutandpaste.cfg
collective/cutandpaste/tests.py
collective/cutandpaste/zope2.py
collective/cutandpaste/profiles/default/transmogrifier.txt
docs/HISTORY.txt