Metadata-Version: 1.0
Name: collective.cutandpaste
Version: 1.0
Summary: for copy and paste items for plone with an csv file
Home-page: http://svn.plone.org/svn/collective/
Author: yboussard
Author-email: y.boussard@free.fr
License: GPL
Keywords: transmogrifier plone
Platform: UNKNOWN
Classifier: Programming Language :: Python
Classifier: Framework :: Plone
Classifier: Framework :: Plone :: 3.3
Classifier: Intended Audience :: Developers
Classifier: License :: OSI Approved :: GNU General Public License (GPL)
